privydns/__init__.py
privydns/exceptions.py
privydns/logging.py
privydns/resolver.py
privydns-0.1.4.dist-info/licenses/LICENSE
tests/__init__.py
tests/test_resolver.py
privydns-0.1.4.dist-info/METADATA
privydns-0.1.4.dist-info/WHEEL
privydns-0.1.4.dist-info/top_level.txt
privydns-0.1.4.dist-info/RECORD
