Metadata-Version: 2.4
Name: PrivyDNS
Version: 0.1.4
Summary: A Python library for secure DNS resolution (DoH, DoT, mTLS) with sync & async support.
Author: Nicholas Adamou
Author-email: nicholas.adamou@outlook.com
Classifier: Programming Language :: Python :: 3
Classifier: License :: OSI Approved :: MIT License
Classifier: Operating System :: OS Independent
License-File: LICENSE
Dynamic: author
Dynamic: author-email
Dynamic: classifier
Dynamic: description
Dynamic: description-content-type
Dynamic: license-file
Dynamic: summary
